nwhy.cpython-39-x86_64-linux-gnu.so
nwhy-0.0.15.dist-info/LICENSE
nwhy-0.0.15.dist-info/METADATA
nwhy-0.0.15.dist-info/WHEEL
nwhy-0.0.15.dist-info/top_level.txt
nwhy-0.0.15.dist-info/RECORD
