Metadata-Version: 2.1
Name: nwhy
Version: 0.0.15
Summary: NWhy project using pybind11 and CMake
Home-page: https://pypi.org/project/nwhy/
Author: Xu Tony Liu
Author-email: xu.liu2@wsu.edu
License: BSD license
Platform: Linux
Platform: Mac OS-X
Platform: Unix
Classifier: Development Status :: 3 - Alpha
Classifier: Intended Audience :: Developers
Classifier: Topic :: Software Development :: Build Tools
Classifier: License :: OSI Approved :: BSD License
Classifier: Programming Language :: Python :: 3.9
Requires-Python: >=3.9
